filepreviewfields
